LICENSE
README.md
wit_core/__init__.py
wit_core/api/http_server.py
wit_core/api/websocket_server.py
wit_core/chatbot.py
wit_core/cli/__init__.py
wit_core/cli/cli.py
wit_core/cli/http_server.py
wit_core/cli/initial_project/actions/__init__.py
wit_core/cli/initial_project/actions/actions.py
wit_core/cli/initial_project/domain.yaml
wit_core/cli/initial_project/templates/__init__.py
wit_core/cli/initial_project/templates/templates.py
wit_core/cli/initial_project/tests/__init__.py
wit_core/cli/initial_project/tests/test_app.py
wit_core/cli/scafolld.py
wit_core/cli/shell.py
wit_core/cli/websocket_server.py
wit_core/core/__init__.py
wit_core/core/domain.py
wit_core/core/process.py
wit_core/core/utils.py
wit_core/decorators.py
wit_core/tests/__init__.py
wit_core/tests/conftest.py
wit_core/tests/test_domain.py
wit_core/tests/test_http_server.py
wit_core/tests/test_process.py
wit_core/tests/test_websocket_server.py
wit_core/tests/utilities.py
wit_core-0.1.6.dist-info/entry_points.txt
wit_core-0.1.6.dist-info/LICENSE
wit_core-0.1.6.dist-info/WHEEL
wit_core-0.1.6.dist-info/METADATA
wit_core-0.1.6.dist-info/RECORD
