Metadata-Version: 2.1
Name: wit-core
Version: 0.1.6
Summary: Response processor for wit.ai
Home-page: https://github.com/LucasOliveiraS/wit-core
License: MIT
Keywords: bot,bots,botkit,wit,wit-ai,wit-core,conversational-ai,chatbot,chatbot-framework,bot-framework
Author: Lucas Oliveira
Author-email: ls.oliveiras.santos@gmail.com
Requires-Python: >3.6.1,<4
Classifier: License :: OSI Approved :: MIT License
Classifier: Operating System :: OS Independent
Classifier: Programming Language :: Python :: 3
Classifier: Programming Language :: Python :: 3.7
Classifier: Programming Language :: Python :: 3.8
Classifier: Programming Language :: Python :: 3.9
Requires-Dist: PyYAML (>=5.4.1,<6.0.0)
Requires-Dist: click (>=7.1.2,<8.0.0)
Requires-Dist: fastapi (>=0.63.0,<0.64.0)
Requires-Dist: loguru (>=0.5.3,<0.6.0)
Requires-Dist: pampy (>=0.3.0,<0.4.0)
Requires-Dist: python-dotenv (>=0.17.0,<0.18.0)
Requires-Dist: uvicorn (>=0.13.4,<0.14.0)
Requires-Dist: wit (>=6.0.0,<7.0.0)
Project-URL: Documentation, https://github.com/LucasOliveiraS/wit-core
Project-URL: Repository, https://github.com/LucasOliveiraS/wit-core
